MANIFEST.in
README.md
setup.cfg
setup.py
ovation/__init__.py
ovation/activities.py
ovation/cli.py
ovation/contents.py
ovation/core.py
ovation/download.py
ovation/service.py
ovation/session.py
ovation/transfer.py
ovation/upload.py
ovation/util.py
ovation.egg-info/PKG-INFO
ovation.egg-info/SOURCES.txt
ovation.egg-info/dependency_links.txt
ovation.egg-info/not-zip-safe
ovation.egg-info/requires.txt
ovation.egg-info/top_level.txt
ovation/lab/__init__.py
ovation/lab/constants.py
ovation/lab/download.py
ovation/lab/reports.py
ovation/lab/requisitions.py
ovation/lab/resources.py
ovation/lab/results.py
ovation/lab/session.py
ovation/lab/upload.py
ovation/lab/workflows.py
test/test_activities.py
test/test_contents.py
test/test_core.py
test/test_download.py
test/test_reports.py
test/test_session.py
test/test_transfer.py
test/test_upload.py
test/test_workflows.py