Metadata-Version: 1.1
Name: ovation
Version: 1.25.0
Summary: Ovation Python API
Home-page: https://ovation.io
Author: Ovation.io, Inc.
Author-email: info@ovation.io
License: UNKNOWN
Platform: UNKNOWN
Classifier: Development Status :: 4 - Beta
Classifier: Intended Audience :: Science/Research
Classifier: License :: OSI Approved :: GNU General Public License v3 (GPLv3)
